leonardo_3d_viewer
